README.rst
setup.py
webid_delegated_auth/__init__.py
webid_delegated_auth/client.py
webid_delegated_auth/exceptions.py
webid_delegated_auth/signing.py
webid_delegated_auth.egg-info/PKG-INFO
webid_delegated_auth.egg-info/SOURCES.txt
webid_delegated_auth.egg-info/dependency_links.txt
webid_delegated_auth.egg-info/requires.txt
webid_delegated_auth.egg-info/top_level.txt