Metadata-Version: 1.1
Name: webid-delegated-auth
Version: 0.1
Summary: WebID delegated authentication tools (signing and checking auth URLs)
Home-page: https://github.com/bcogrel/webid-delegated-auth
Author: Benjamin Cogrel
Author-email: benjamin.cogrel@bcgl.fr
License: MIT
Platform: UNKNOWN
Classifier: Development Status :: 4 - Beta
Classifier: Intended Audience :: Developers
Classifier: License :: OSI Approved :: BSD License
Classifier: Programming Language :: Python
Classifier: Programming Language :: Python :: 2
Classifier: Programming Language :: Python :: 2.7
Classifier: Topic :: Software Development :: Libraries
